LICENSE
MANIFEST.in
README.md
requirements.txt
setup.py
src/acrobotics/__init__.py
src/acrobotics/geometry.py
src/acrobotics/irlio.py
src/acrobotics/link.py
src/acrobotics/robot.py
src/acrobotics/robot_examples.py
src/acrobotics/shapes.py
src/acrobotics/tool_examples.py
src/acrobotics/urdfio.py
src/acrobotics/workspace_envelope.py
src/acrobotics.egg-info/PKG-INFO
src/acrobotics.egg-info/SOURCES.txt
src/acrobotics.egg-info/dependency_links.txt
src/acrobotics.egg-info/requires.txt
src/acrobotics.egg-info/top_level.txt
src/acrobotics/inverse_kinematics/__init__.py
src/acrobotics/inverse_kinematics/anthropomorphic_arm.py
src/acrobotics/inverse_kinematics/arm_2.py
src/acrobotics/inverse_kinematics/ik_result.py
src/acrobotics/inverse_kinematics/planar_arm.py
src/acrobotics/inverse_kinematics/spherical_wrist.py
src/acrobotics/path/__init__.py
src/acrobotics/path/factory.py
src/acrobotics/path/path_pt.py
src/acrobotics/path/path_pt_base.py
src/acrobotics/path/sampling.py
src/acrobotics/path/tolerance.py
src/acrobotics/path/util.py
src/acrobotics/planning/__init__.py
src/acrobotics/planning/optimization_based.py
src/acrobotics/planning/sampling_based.py
src/acrobotics/planning/settings.py
src/acrobotics/planning/solver.py
src/acrobotics/planning/types.py