Metadata-Version: 2.1
Name: acrobotics
Version: 0.0.6
Summary: Primitive robot kinematics and collision checking.
Home-page: https://github.com/JeroenDM/acrobotics
Author: Jeroen De Maeyer
Author-email: jeroen.demaeyer@kuleuven.be
License: UNKNOWN
Platform: UNKNOWN
Classifier: Programming Language :: Python :: 3
Classifier: License :: OSI Approved :: MIT License
Classifier: Operating System :: OS Independent
Requires-Python: >=3.6
